AD/AD_forward.py
AD/AD_reverse.py
AD/Dual.py
AD/Node.py
AD/__init__.py
AD/elementary.py
AD/elementary_node.py
swiftdiff-0.0.2.dist-info/LICENSE
swiftdiff-0.0.2.dist-info/METADATA
swiftdiff-0.0.2.dist-info/WHEEL
swiftdiff-0.0.2.dist-info/top_level.txt
swiftdiff-0.0.2.dist-info/RECORD
