Metadata-Version: 2.1
Name: swiftdiff
Version: 0.0.2
Summary: SwiftDiff performs automatic differentiation (AD) for the user.
Home-page: https://github.com/cs107-swiftdiff/cs107-FinalProject
Author: Nadine Lee, Li Sun, Alice Cai
Author-email: nadine_lee@college.harvard.edu, lsun@g.harvard.edu, acai@college.harvard.edu
License: UNKNOWN
Project-URL: Bug Tracker, https://github.com/cs107-swiftdiff/cs107-FinalProject/issues
Platform: UNKNOWN
Classifier: Programming Language :: Python :: 3
Classifier: License :: OSI Approved :: GNU General Public License v3 (GPLv3)
Classifier: Operating System :: OS Independent
Requires-Python: >=3.6
License-File: LICENSE
